casatunes/__init__.py
casatunes/core.py
casatunes/player.py
casatunes/zone.py
casatunes-0.0.5.dist-info/LICENSE
casatunes-0.0.5.dist-info/METADATA
casatunes-0.0.5.dist-info/WHEEL
casatunes-0.0.5.dist-info/top_level.txt
casatunes-0.0.5.dist-info/RECORD
