Metadata-Version: 2.1
Name: casatunes
Version: 0.0.5
Summary: Simple library for CasaTunes REST API
Home-page: https://github.com/resoai/casatunes
Author: Alexey Ivanov
Author-email: me@reso.od.ua
License: UNKNOWN
Platform: UNKNOWN
Classifier: Programming Language :: Python :: 3
Classifier: License :: OSI Approved :: MIT License
Classifier: Operating System :: OS Independent
Requires-Dist: validators
